aaaaa_cursed-for.pth
cursed_for/__init__.py
cursed_for/console.py
cursed_for/errors.py
cursed_for-0.3.0.dist-info/LICENSE
cursed_for-0.3.0.dist-info/METADATA
cursed_for-0.3.0.dist-info/WHEEL
cursed_for-0.3.0.dist-info/entry_points.txt
cursed_for-0.3.0.dist-info/top_level.txt
cursed_for-0.3.0.dist-info/RECORD
